zero_motorcycles/__about__.py
zero_motorcycles/__init__.py
zero_motorcycles/api.py
zero_motorcycles/model.py
zero_motorcycles-3.0.0.dist-info/METADATA
zero_motorcycles-3.0.0.dist-info/WHEEL
zero_motorcycles-3.0.0.dist-info/licenses/LICENSE.txt
zero_motorcycles-3.0.0.dist-info/RECORD
