Metadata-Version: 2.3
Name: zero-motorcycles
Version: 3.0.0
Project-URL: Documentation, https://github.com/mattzuba/zero-motorcycles#readme
Project-URL: Issues, https://github.com/mattzuba/zero-motorcycles/issues
Project-URL: Source, https://github.com/mattzuba/zero-motorcycles
Author-email: Matt Zuba <matt.zuba@gmail.com>
License-Expression: BSD-3-Clause
License-File: LICENSE.txt
Classifier: Development Status :: 4 - Beta
Classifier: Programming Language :: Python
Classifier: Programming Language :: Python :: 3.11
Classifier: Programming Language :: Python :: 3.12
Classifier: Programming Language :: Python :: Implementation :: CPython
Classifier: Programming Language :: Python :: Implementation :: PyPy
Requires-Python: >=3.7
Requires-Dist: aiohttp>=3.9.0
Requires-Dist: async-timeout>=4.0.0
Requires-Dist: pycryptodome>=3.20.0
